MANIFEST.in
setup.py
renderthreads/__init__.py
renderthreads/renderthreads.py
renderthreads.egg-info/PKG-INFO
renderthreads.egg-info/SOURCES.txt
renderthreads.egg-info/dependency_links.txt
renderthreads.egg-info/not-zip-safe
renderthreads.egg-info/top_level.txt
renderthreads/lib/__init__.py
renderthreads/lib/renderthreads_command_line_engine.py
renderthreads/lib/renderthreads_globals.py
renderthreads/lib/renderthreads_gui_setup.py
renderthreads/lib/renderthreads_logging.py
renderthreads/lib/renderthreads_mvc_setup.py
renderthreads/lib/renderthreads_nuke.py
renderthreads/lib/renderthreads_render.py
renderthreads/lib/renderthreads_services_setup.py
renderthreads/lib/renderthreads_threads.py
renderthreads/lib/gui/__init__.py
renderthreads/lib/gui/renderthreads_command_line_flag_widget.py
renderthreads/lib/gui/renderthreads_dock_widget.py
renderthreads/lib/gui/renderthreads_gui_helper.py
renderthreads/lib/gui/renderthreads_progressbar.py
renderthreads/lib/gui/renderthreads_signal_remapper.py
renderthreads/lib/gui/renderthreads_slider_widget.py
renderthreads/lib/gui/renderthreads_stylesheets.py
renderthreads/lib/mvc/__init__.py
renderthreads/lib/mvc/renderthreads_item_delegate.py
renderthreads/lib/mvc/renderthreads_model.py
renderthreads/lib/mvc/renderthreads_model_context_menu.py
renderthreads/lib/mvc/renderthreads_node.py
renderthreads/lib/mvc/renderthreads_view.py
renderthreads/lib/third_party/__init__.py
renderthreads/lib/third_party/pysideuic/__init__.py
renderthreads/lib/third_party/pysideuic/__init__.pyc
renderthreads/lib/third_party/pysideuic/__init__.pyo
renderthreads/lib/third_party/pysideuic/driver.py
renderthreads/lib/third_party/pysideuic/driver.pyc
renderthreads/lib/third_party/pysideuic/driver.pyo
renderthreads/lib/third_party/pysideuic/exceptions.py
renderthreads/lib/third_party/pysideuic/exceptions.pyc
renderthreads/lib/third_party/pysideuic/exceptions.pyo
renderthreads/lib/third_party/pysideuic/icon_cache.py
renderthreads/lib/third_party/pysideuic/icon_cache.pyc
renderthreads/lib/third_party/pysideuic/icon_cache.pyo
renderthreads/lib/third_party/pysideuic/objcreator.py
renderthreads/lib/third_party/pysideuic/objcreator.pyc
