Metadata-Version: 1.1
Name: renderthreads
Version: 0.3.1
Summary: Package that enables easy command-line multithreaded rendering for Nuke.
Home-page: https://github.com/timmwagener/renderthreads
Author: Timm Wagener
Author-email: wagenertimm@gmail.com
License: MIT
Keywords: Foundy TheFoundry Nuke Pipeline Compositing Filmakademie Timm Wagener Multithreading Commandline Rendering
Platform: UNKNOWN
Classifier: Development Status :: 4 - Beta
Classifier: Intended Audience :: End Users/Desktop
Classifier: Operating System :: Microsoft :: Windows
Classifier: Programming Language :: Python
Classifier: Topic :: Software Development
Classifier: Topic :: Utilities
Classifier: Topic :: Multimedia
Classifier: Topic :: Multimedia :: Graphics
Classifier: Topic :: Multimedia :: Graphics :: 3D Rendering
Classifier: Topic :: Multimedia :: Graphics :: Graphics Conversion
Classifier: Topic :: Multimedia :: Graphics :: Presentation
Classifier: Topic :: Multimedia :: Video
Classifier: Topic :: Multimedia :: Video :: Conversion
Classifier: Topic :: Multimedia :: Video :: Display
Classifier: Topic :: Multimedia :: Video :: Non-Linear Editor
Classifier: Topic :: Documentation :: Sphinx
